Workbook

Sheet Summary
A1: Loan tape review (demo data)
A2: As of 2026-10-31. All names, amounts and dates are fictitious.
A4: What the information establishes
A5: - 24 loans in the tape; 18 active with 2,565,000 outstanding principal.
A6: - Cash per ledger: 276,810.
A7: - 6 loans paid off; average time from funding to payoff 165 days.
A8: - Largest borrower exposure: B03 with 13% of active principal.
A10: What is assumed
A11: - Interest is paid at payoff (principal x 12% x term).
A12: - Active loans pay off at maturity in the base case; loans already past maturity pay next month.
A13: - Delayed case: every payoff moves by the number of months in Assumptions!B3.
A14: - New loans: count, size, term and rate as set in Assumptions; they pay off after their term.
... A25: - Use 'Capital needed' in Forecast as the size of the next capital raise, plus the cash buffer.
A27: Capital needed (base case) | B27: =Forecast!I18
A28: Capital needed (delayed payoffs) | B28: =Forecast!J18

Sheet Issues
A1: Severity | B1: Loan | C1: Issue | D1: Evidence | E1: Proposed resolution
A2: High | B2: L-0107 | C2: Funding in tape but not in ledger | D2: Tape: 185,000 funded 2026-01-31; ledger: no funding row | E2: Request bank statement for the funding date; book the missing ledger entry or correct the tape
A3: High | B3: L-0109 | C3: Tape says paid off, ledger has no payoff | D3: Tape payoff 89,107.95 on 2026-07-26 | E3: Find the payoff receipt; if not received, the loan is still outstanding
A4: High | B4: L-0115 | C4: Duplicate funding in ledger | D4: 2 funding rows totalling 320,000 vs tape principal 160,000 | E4: Confirm against bank statement and reverse the duplicate ledger row
A5: High | B5: L-0125 | C5: Funding in ledger for a loan not in tape | D5: Ledger funding 95,000 | E5: Obtain loan documents and add to tape, or reverse if posted in error
A6: Medium | B6: L-0105 | C6: Active loan past maturity | D6: Matured 2026-07-02, 121 days ago | E6: Confirm extension terms or start default process; treat payoff as delayed in the forecast
A7: Medium | B7: L-0111 | C7: Active loan past maturity | D7: Matured 2026-09-30, 31 days ago | E7: Confirm extension terms or start default process; treat payoff as delayed in the forecast
A8: Medium | B8: L-0112 | C8: Payoff amount differs | D8: Tape 89,974.25 vs ledger 87,474.25 (diff -2,500.00) | E8: Check payoff statement: fees, interest days or a short payment
A9: Low | B9: L-0103 | C9: Funding date differs | D9: Tape 2025-12-04 vs ledger 2025-12-10 (6 days) | E9: Use the bank value date in both records; affects interest accrual

Sheet Reconciliation
A1: Loan | B1: Borrower | C1: Status (tape) | D1: Principal (tape) | E1: Funding (ledger) | F1: Payoff (tape) | G1: Payoff (ledger) | H1: Result
A2: L-0101 | B2: B01 | C2: Active | D2: 185000 | E2: 185000 | H2: OK
A3: L-0102 | B3: B02 | C3: Paid off | D3: 85000 | E3: 85000 | F3: 90030.14 | G3: 90030.14 | H3: OK
A4: L-0103 | B4: B03 | C4: Paid off | D4: 185000 | E4: 185000 | F4: 195035.62 | G4: 195035.62 | H4: Check
A5: L-0104 | B5: B03 | C5: Active | D5: 110000 | E5: 110000 | H5: OK
A6: L-0105 | B6: B03 | C6: Active | D6: 110000 | E6: 110000 | H6: Check
A7: L-0106 | B7: B04 | C7: Paid off | D7: 110000 | E7: 110000 | F7: 116328.77 | G7: 116328.77 | H7: OK
A8: L-0107 | B8: B05 | C8: Active | D8: 185000 | E8: 0 | H8: Check
A9: L-0108 | B9: B06 | C9: Paid off | D9: 185000 | E9: 185000 | F9: 193940.82 | G9: 193940.82 | H9: OK
A10: L-0109 | B10: B03 | C10: Paid off | D10: 85000 | E10: 85000 | F10: 89107.95 | H10: Check
A11: L-0110 | B11: B07 | C11: Active | D11: 140000 | E11: 140000 | H11: OK
A12: L-0111 | B12: B08 | C12: Active | D12: 85000 | E12: 85000 | H12: Check
A13: L-0112 | B13: B02 | C13: Paid off | D13: 85000 | E13: 85000 | F13: 89974.25 | G13: 87474.25 | H13: Check
A14: L-0113 | B14: B09 | C14: Active | D14: 110000 | E14: 110000 | H14: OK
A15: L-0114 | B15: B03 | C15: Active | D15: 110000 | E15: 110000 | H15: OK
A16: L-0115 | B16: B10 | C16: Active | D16: 160000 | E16: 320000 | H16: Check
A17: L-0116 | B17: B11 | C17: Active | D17: 160000 | E17: 160000 | H17: OK
A18: L-0117 | B18: B12 | C18: Active | D18: 85000 | E18: 85000 | H18: OK
A19: L-0118 | B19: B02 | C19: Active | D19: 160000 | E19: 160000 | H19: OK
A20: L-0119 | B20: B13 | C20: Active | D20: 110000 | E20: 110000 | H20: OK
A21: L-0120 | B21: B14 | C21: Active | D21: 185000 | E21: 185000 | H21: OK
A22: L-0121 | B22: B15 | C22: Active | D22: 185000 | E22: 185000 | H22: OK
A23: L-0122 | B23: B16 | C23: Active | D23: 185000 | E23: 185000 | H23: OK
A24: L-0123 | B24: B17 | C24: Active | D24: 160000 | E24: 160000 | H24: OK
A25: L-0124 | B25: B18 | C25: Active | D25: 140000 | E25: 140000 | H25: OK

Sheet Portfolio
A1: Concentration by borrower (active principal)
A2: Borrower | B2: Active principal | C2: Share
A3: B03 | B3: 330000 | C3: 0.12865497
A4: B01 | B4: 185000 | C4: 0.072124756
A5: B05 | B5: 185000 | C5: 0.072124756
A6: B14 | B6: 185000 | C6: 0.072124756
A7: B15 | B7: 185000 | C7: 0.072124756
A8: B16 | B8: 185000 | C8: 0.072124756
A9: B10 | B9: 160000 | C9: 0.062378168
A10: B02 | B10: 160000 | C10: 0.062378168
A11: B17 | B11: 160000 | C11: 0.062378168
A12: B11 | B12: 160000 | C12: 0.062378168
A13: B07 | B13: 140000 | C13: 0.054580897
A14: B18 | B14: 140000 | C14: 0.054580897
... A18: B12 | B18: 85000 | C18: 0.033138402
A20: Loans past maturity
A21: Loan | B21: Borrower | C21: Principal | D21: Maturity | E21: Days past
A22: L-0105 | B22: B03 | C22: 110000 | D22: 46205 | E22: 121
A23: L-0111 | B23: B08 | C23: 85000 | D23: 46295 | E23: 31
A25: Paid-off loans: days from funding to payoff
A26: Average | B26: 165
A27: Shortest | B27: 147
A28: Longest | B28: 180

Sheet Assumptions
A1: Input | B1: Value | C1: Note
A2: As-of date | B2: 46326 | C2: Ledger cash is measured on this date
A3: Payoff delay (months) | B3: 2 | C3: Delayed case: months added to every expected payoff
A4: New loans per month | B4: 2 | C4: Pipeline assumption - confirm with lender
A5: Average new loan | B5: 150000 | C5: Average principal of new loans
A6: Investor distributions per month | B6: 20000 | C6: From ledger history
A7: Operating costs per month | B7: 8000 | C7: From ledger history
A8: Minimum cash buffer | B8: 100000 | C8: Cash the lender wants to keep at all times
A9: Opening cash | B9: 276809.6 | C9: Ledger balance on the as-of date
A10: Term of new loans (months) | B10: 6 | C10: New loans pay off after this many months
A11: Interest rate on new loans | B11: 0.12 | C11: Annual, paid at payoff

Sheet Loans
A1: Loan | B1: Borrower | C1: Principal | D1: Maturity | E1: Expected payoff month | F1: Delayed payoff month | G1: Payoff amount
A2: L-0101 | B2: B01 | C2: 185000 | D2: 46331 | E2: =IF(D2<=Assumptions!$B$2,EOMONTH(Assumptions!$B$2,1),EOMONTH(D2,0)) | F2: =EOMONTH(E2,Assumptions!$B$3) | G2: =C2*(1+0.12*12/12)
A3: L-0104 | B3: B03 | C3: 110000 | D3: 46374 | E3: =IF(D3<=Assumptions!$B$2,EOMONTH(Assumptions!$B$2,1),EOMONTH(D3,0)) | F3: =EOMONTH(E3,Assumptions!$B$3) | G3: =C3*(1+0.12*12/12)
A4: L-0105 | B4: B03 | C4: 110000 | D4: 46205 | E4: =IF(D4<=Assumptions!$B$2,EOMONTH(Assumptions!$B$2,1),EOMONTH(D4,0)) | F4: =EOMONTH(E4,Assumptions!$B$3) | G4: =C4*(1+0.12*6/12)
A5: L-0107 | B5: B05 | C5: 185000 | D5: 46418 | E5: =IF(D5<=Assumptions!$B$2,EOMONTH(Assumptions!$B$2,1),EOMONTH(D5,0)) | F5: =EOMONTH(E5,Assumptions!$B$3) | G5: =C5*(1+0.12*12/12)
A6: L-0110 | B6: B07 | C6: 140000 | D6: 46461 | E6: =IF(D6<=Assumptions!$B$2,EOMONTH(Assumptions!$B$2,1),EOMONTH(D6,0)) | F6: =EOMONTH(E6,Assumptions!$B$3) | G6: =C6*(1+0.12*12/12)
A7: L-0111 | B7: B08 | C7: 85000 | D7: 46295 | E7: =IF(D7<=Assumptions!$B$2,EOMONTH(Assumptions!$B$2,1),EOMONTH(D7,0)) | F7: =EOMONTH(E7,Assumptions!$B$3) | G7: =C7*(1+0.12*6/12)
A8: L-0113 | B8: B09 | C8: 110000 | D8: 46505 | E8: =IF(D8<=Assumptions!$B$2,EOMONTH(Assumptions!$B$2,1),EOMONTH(D8,0)) | F8: =EOMONTH(E8,Assumptions!$B$3) | G8: =C8*(1+0.12*12/12)
A9: L-0114 | B9: B03 | C9: 110000 | D9: 46338 | E9: =IF(D9<=Assumptions!$B$2,EOMONTH(Assumptions!$B$2,1),EOMONTH(D9,0)) | F9: =EOMONTH(E9,Assumptions!$B$3) | G9: =C9*(1+0.12*6/12)
A10: L-0115 | B10: B10 | C10: 160000 | D10: 46353 | E10: =IF(D10<=Assumptions!$B$2,EOMONTH(Assumptions!$B$2,1),EOMONTH(D10,0)) | F10: =EOMONTH(E10,Assumptions!$B$3) | G10: =C10*(1+0.12*6/12)
A11: L-0116 | B11: B11 | C11: 160000 | D11: 46548 | E11: =IF(D11<=Assumptions!$B$2,EOMONTH(Assumptions!$B$2,1),EOMONTH(D11,0)) | F11: =EOMONTH(E11,Assumptions!$B$3) | G11: =C11*(1+0.12*12/12)
A12: L-0117 | B12: B12 | C12: 85000 | D12: 46381 | E12: =IF(D12<=Assumptions!$B$2,EOMONTH(Assumptions!$B$2,1),EOMONTH(D12,0)) | F12: =EOMONTH(E12,Assumptions!$B$3) | G12: =C12*(1+0.12*6/12)
A13: L-0118 | B13: B02 | C13: 160000 | D13: 46396 | E13: =IF(D13<=Assumptions!$B$2,EOMONTH(Assumptions!$B$2,1),EOMONTH(D13,0)) | F13: =EOMONTH(E13,Assumptions!$B$3) | G13: =C13*(1+0.12*6/12)
A14: L-0119 | B14: B13 | C14: 110000 | D14: 46592 | E14: =IF(D14<=Assumptions!$B$2,EOMONTH(Assumptions!$B$2,1),EOMONTH(D14,0)) | F14: =EOMONTH(E14,Assumptions!$B$3) | G14: =C14*(1+0.12*12/12)
A15: L-0120 | B15: B14 | C15: 185000 | D15: 46425 | E15: =IF(D15<=Assumptions!$B$2,EOMONTH(Assumptions!$B$2,1),EOMONTH(D15,0)) | F15: =EOMONTH(E15,Assumptions!$B$3) | G15: =C15*(1+0.12*6/12)
A16: L-0121 | B16: B15 | C16: 185000 | D16: 46440 | E16: =IF(D16<=Assumptions!$B$2,EOMONTH(Assumptions!$B$2,1),EOMONTH(D16,0)) | F16: =EOMONTH(E16,Assumptions!$B$3) | G16: =C16*(1+0.12*6/12)
A17: L-0122 | B17: B16 | C17: 185000 | D17: 46635 | E17: =IF(D17<=Assumptions!$B$2,EOMONTH(Assumptions!$B$2,1),EOMONTH(D17,0)) | F17: =EOMONTH(E17,Assumptions!$B$3) | G17: =C17*(1+0.12*12/12)
A18: L-0123 | B18: B17 | C18: 160000 | D18: 46466 | E18: =IF(D18<=Assumptions!$B$2,EOMONTH(Assumptions!$B$2,1),EOMONTH(D18,0)) | F18: =EOMONTH(E18,Assumptions!$B$3) | G18: =C18*(1+0.12*6/12)
A19: L-0124 | B19: B18 | C19: 140000 | D19: 46481 | E19: =IF(D19<=Assumptions!$B$2,EOMONTH(Assumptions!$B$2,1),EOMONTH(D19,0)) | F19: =EOMONTH(E19,Assumptions!$B$3) | G19: =C19*(1+0.12*6/12)

Sheet Forecast
A1: 12-month cash forecast: base vs delayed payoffs
A2: Edit the yellow inputs in Assumptions; every figure below recalculates.
A3: Month | B3: Payoffs, existing loans (base) | C3: Payoffs, existing loans (delayed) | D3: New fundings | E3: Payoffs, new loans (base) | F3: Payoffs, new loans (delayed) | G3: Investor distributions | H3: Operating costs | I3: Closing cash (base) | J3: Closing cash (delayed)
A4: =EOMONTH(Assumptions!$B$2,1) | B4: =SUMIFS(Loans!$G$2:$G$19,Loans!$E$2:$E$19,A4) | C4: =SUMIFS(Loans!$G$2:$G$19,Loans!$F$2:$F$19,A4) | D4: =Assumptions!$B$4*Assumptions!$B$5 | E4: =IF(ROW()-3>Assumptions!$B$10,OFFSET(D4,-Assumptions!$B$10,0)*(1+Assumptions!$B$11*Assumptions!$B$10/12),0) | F4: =IF(ROW()-3>Assumptions!$B$10+Assumptions!$B$3,OFFSET(D4,-(Assumptions!$B$10+Assumptions!$B$3),0)*(1+Assumptions!$B$11*Assumptions!$B$10/12),0) | G4: =Assumptions!$B$6 | H4: =Assumptions!$B$7 | I4: =Assumptions!$B$9+B4+E4-D4-G4-H4 | J4: =Assumptions!$B$9+C4+F4-D4-G4-H4
A5: =EOMONTH(Assumptions!$B$2,2) | B5: =SUMIFS(Loans!$G$2:$G$19,Loans!$E$2:$E$19,A5) | C5: =SUMIFS(Loans!$G$2:$G$19,Loans!$F$2:$F$19,A5) | D5: =Assumptions!$B$4*Assumptions!$B$5 | E5: =IF(ROW()-3>Assumptions!$B$10,OFFSET(D5,-Assumptions!$B$10,0)*(1+Assumptions!$B$11*Assumptions!$B$10/12),0) | F5: =IF(ROW()-3>Assumptions!$B$10+Assumptions!$B$3,OFFSET(D5,-(Assumptions!$B$10+Assumptions!$B$3),0)*(1+Assumptions!$B$11*Assumptions!$B$10/12),0) | G5: =Assumptions!$B$6 | H5: =Assumptions!$B$7 | I5: =I4+B5+E5-D5-G5-H5 | J5: =J4+C5+F5-D5-G5-H5
A6: =EOMONTH(Assumptions!$B$2,3) | B6: =SUMIFS(Loans!$G$2:$G$19,Loans!$E$2:$E$19,A6) | C6: =SUMIFS(Loans!$G$2:$G$19,Loans!$F$2:$F$19,A6) | D6: =Assumptions!$B$4*Assumptions!$B$5 | E6: =IF(ROW()-3>Assumptions!$B$10,OFFSET(D6,-Assumptions!$B$10,0)*(1+Assumptions!$B$11*Assumptions!$B$10/12),0) | F6: =IF(ROW()-3>Assumptions!$B$10+Assumptions!$B$3,OFFSET(D6,-(Assumptions!$B$10+Assumptions!$B$3),0)*(1+Assumptions!$B$11*Assumptions!$B$10/12),0) | G6: =Assumptions!$B$6 | H6: =Assumptions!$B$7 | I6: =I5+B6+E6-D6-G6-H6 | J6: =J5+C6+F6-D6-G6-H6
A7: =EOMONTH(Assumptions!$B$2,4) | B7: =SUMIFS(Loans!$G$2:$G$19,Loans!$E$2:$E$19,A7) | C7: =SUMIFS(Loans!$G$2:$G$19,Loans!$F$2:$F$19,A7) | D7: =Assumptions!$B$4*Assumptions!$B$5 | E7: =IF(ROW()-3>Assumptions!$B$10,OFFSET(D7,-Assumptions!$B$10,0)*(1+Assumptions!$B$11*Assumptions!$B$10/12),0) | F7: =IF(ROW()-3>Assumptions!$B$10+Assumptions!$B$3,OFFSET(D7,-(Assumptions!$B$10+Assumptions!$B$3),0)*(1+Assumptions!$B$11*Assumptions!$B$10/12),0) | G7: =Assumptions!$B$6 | H7: =Assumptions!$B$7 | I7: =I6+B7+E7-D7-G7-H7 | J7: =J6+C7+F7-D7-G7-H7
A8: =EOMONTH(Assumptions!$B$2,5) | B8: =SUMIFS(Loans!$G$2:$G$19,Loans!$E$2:$E$19,A8) | C8: =SUMIFS(Loans!$G$2:$G$19,Loans!$F$2:$F$19,A8) | D8: =Assumptions!$B$4*Assumptions!$B$5 | E8: =IF(ROW()-3>Assumptions!$B$10,OFFSET(D8,-Assumptions!$B$10,0)*(1+Assumptions!$B$11*Assumptions!$B$10/12),0) | F8: =IF(ROW()-3>Assumptions!$B$10+Assumptions!$B$3,OFFSET(D8,-(Assumptions!$B$10+Assumptions!$B$3),0)*(1+Assumptions!$B$11*Assumptions!$B$10/12),0) | G8: =Assumptions!$B$6 | H8: =Assumptions!$B$7 | I8: =I7+B8+E8-D8-G8-H8 | J8: =J7+C8+F8-D8-G8-H8
A9: =EOMONTH(Assumptions!$B$2,6) | B9: =SUMIFS(Loans!$G$2:$G$19,Loans!$E$2:$E$19,A9) | C9: =SUMIFS(Loans!$G$2:$G$19,Loans!$F$2:$F$19,A9) | D9: =Assumptions!$B$4*Assumptions!$B$5 | E9: =IF(ROW()-3>Assumptions!$B$10,OFFSET(D9,-Assumptions!$B$10,0)*(1+Assumptions!$B$11*Assumptions!$B$10/12),0) | F9: =IF(ROW()-3>Assumptions!$B$10+Assumptions!$B$3,OFFSET(D9,-(Assumptions!$B$10+Assumptions!$B$3),0)*(1+Assumptions!$B$11*Assumptions!$B$10/12),0) | G9: =Assumptions!$B$6 | H9: =Assumptions!$B$7 | I9: =I8+B9+E9-D9-G9-H9 | J9: =J8+C9+F9-D9-G9-H9
A10: =EOMONTH(Assumptions!$B$2,7) | B10: =SUMIFS(Loans!$G$2:$G$19,Loans!$E$2:$E$19,A10) | C10: =SUMIFS(Loans!$G$2:$G$19,Loans!$F$2:$F$19,A10) | D10: =Assumptions!$B$4*Assumptions!$B$5 | E10: =IF(ROW()-3>Assumptions!$B$10,OFFSET(D10,-Assumptions!$B$10,0)*(1+Assumptions!$B$11*Assumptions!$B$10/12),0) | F10: =IF(ROW()-3>Assumptions!$B$10+Assumptions!$B$3,OFFSET(D10,-(Assumptions!$B$10+Assumptions!$B$3),0)*(1+Assumptions!$B$11*Assumptions!$B$10/12),0) | G10: =Assumptions!$B$6 | H10: =Assumptions!$B$7 | I10: =I9+B10+E10-D10-G10-H10 | J10: =J9+C10+F10-D10-G10-H10
A11: =EOMONTH(Assumptions!$B$2,8) | B11: =SUMIFS(Loans!$G$2:$G$19,Loans!$E$2:$E$19,A11) | C11: =SUMIFS(Loans!$G$2:$G$19,Loans!$F$2:$F$19,A11) | D11: =Assumptions!$B$4*Assumptions!$B$5 | E11: =IF(ROW()-3>Assumptions!$B$10,OFFSET(D11,-Assumptions!$B$10,0)*(1+Assumptions!$B$11*Assumptions!$B$10/12),0) | F11: =IF(ROW()-3>Assumptions!$B$10+Assumptions!$B$3,OFFSET(D11,-(Assumptions!$B$10+Assumptions!$B$3),0)*(1+Assumptions!$B$11*Assumptions!$B$10/12),0) | G11: =Assumptions!$B$6 | H11: =Assumptions!$B$7 | I11: =I10+B11+E11-D11-G11-H11 | J11: =J10+C11+F11-D11-G11-H11
A12: =EOMONTH(Assumptions!$B$2,9) | B12: =SUMIFS(Loans!$G$2:$G$19,Loans!$E$2:$E$19,A12) | C12: =SUMIFS(Loans!$G$2:$G$19,Loans!$F$2:$F$19,A12) | D12: =Assumptions!$B$4*Assumptions!$B$5 | E12: =IF(ROW()-3>Assumptions!$B$10,OFFSET(D12,-Assumptions!$B$10,0)*(1+Assumptions!$B$11*Assumptions!$B$10/12),0) | F12: =IF(ROW()-3>Assumptions!$B$10+Assumptions!$B$3,OFFSET(D12,-(Assumptions!$B$10+Assumptions!$B$3),0)*(1+Assumptions!$B$11*Assumptions!$B$10/12),0) | G12: =Assumptions!$B$6 | H12: =Assumptions!$B$7 | I12: =I11+B12+E12-D12-G12-H12 | J12: =J11+C12+F12-D12-G12-H12
A13: =EOMONTH(Assumptions!$B$2,10) | B13: =SUMIFS(Loans!$G$2:$G$19,Loans!$E$2:$E$19,A13) | C13: =SUMIFS(Loans!$G$2:$G$19,Loans!$F$2:$F$19,A13) | D13: =Assumptions!$B$4*Assumptions!$B$5 | E13: =IF(ROW()-3>Assumptions!$B$10,OFFSET(D13,-Assumptions!$B$10,0)*(1+Assumptions!$B$11*Assumptions!$B$10/12),0) | F13: =IF(ROW()-3>Assumptions!$B$10+Assumptions!$B$3,OFFSET(D13,-(Assumptions!$B$10+Assumptions!$B$3),0)*(1+Assumptions!$B$11*Assumptions!$B$10/12),0) | G13: =Assumptions!$B$6 | H13: =Assumptions!$B$7 | I13: =I12+B13+E13-D13-G13-H13 | J13: =J12+C13+F13-D13-G13-H13
A14: =EOMONTH(Assumptions!$B$2,11) | B14: =SUMIFS(Loans!$G$2:$G$19,Loans!$E$2:$E$19,A14) | C14: =SUMIFS(Loans!$G$2:$G$19,Loans!$F$2:$F$19,A14) | D14: =Assumptions!$B$4*Assumptions!$B$5 | E14: =IF(ROW()-3>Assumptions!$B$10,OFFSET(D14,-Assumptions!$B$10,0)*(1+Assumptions!$B$11*Assumptions!$B$10/12),0) | F14: =IF(ROW()-3>Assumptions!$B$10+Assumptions!$B$3,OFFSET(D14,-(Assumptions!$B$10+Assumptions!$B$3),0)*(1+Assumptions!$B$11*Assumptions!$B$10/12),0) | G14: =Assumptions!$B$6 | H14: =Assumptions!$B$7 | I14: =I13+B14+E14-D14-G14-H14 | J14: =J13+C14+F14-D14-G14-H14
A15: =EOMONTH(Assumptions!$B$2,12) | B15: =SUMIFS(Loans!$G$2:$G$19,Loans!$E$2:$E$19,A15) | C15: =SUMIFS(Loans!$G$2:$G$19,Loans!$F$2:$F$19,A15) | D15: =Assumptions!$B$4*Assumptions!$B$5 | E15: =IF(ROW()-3>Assumptions!$B$10,OFFSET(D15,-Assumptions!$B$10,0)*(1+Assumptions!$B$11*Assumptions!$B$10/12),0) | F15: =IF(ROW()-3>Assumptions!$B$10+Assumptions!$B$3,OFFSET(D15,-(Assumptions!$B$10+Assumptions!$B$3),0)*(1+Assumptions!$B$11*Assumptions!$B$10/12),0) | G15: =Assumptions!$B$6 | H15: =Assumptions!$B$7 | I15: =I14+B15+E15-D15-G15-H15 | J15: =J14+C15+F15-D15-G15-H15
A16: Lowest closing cash | I16: =MIN(I4:I15) | J16: =MIN(J4:J15)
A17: Minimum cash buffer | I17: =Assumptions!$B$8 | J17: =Assumptions!$B$8
A18: Capital needed | I18: =MAX(0,I17-I16) | J18: =MAX(0,J17-J16)
